ysa/__init__.py
ysa/ysa_py.py
ysa-0.1.1.dist-info/METADATA
ysa-0.1.1.dist-info/RECORD
ysa-0.1.1.dist-info/WHEEL
ysa-0.1.1.dist-info/top_level.txt
