Metadata-Version: 2.1
Name: ysa
Version: 0.1.1
Summary: python client for the YSA api
Home-page: https://github.com/sjortiz/YSA-PY
Author: shailyn ortiz(@M_abaader)
Author-email: sortizjim@gmail.com
License: UNKNOWN
Platform: UNKNOWN
Classifier: Programming Language :: Python :: 3
Classifier: License :: OSI Approved :: Apache Software License
Classifier: Operating System :: OS Independent
Requires-Dist: requests
